LICENSE.txt
README.rst
setup.py
pbandplot/__init__.py
pbandplot/plots.py
pbandplot/readdata.py
pbandplot/wrapper.py
pbandplot.egg-info/PKG-INFO
pbandplot.egg-info/SOURCES.txt
pbandplot.egg-info/dependency_links.txt
pbandplot.egg-info/entry_points.txt
pbandplot.egg-info/requires.txt
pbandplot.egg-info/top_level.txt